scheduler/__init__.py
scheduler/admin.py
scheduler/apps.py
scheduler/forms.py
scheduler/models.py
scheduler/tests.py
scheduler/views.py
scheduler/migrations/0001_initial.py
scheduler/migrations/0002_add_timeout.py
scheduler/migrations/0003_remove_queue_choices.py
scheduler/migrations/0004_add_cron_jobs.py
scheduler/migrations/0005_added_result_ttl.py
scheduler/migrations/__init__.py
readwise_django_rq_scheduler-1.2.1.dist-info/LICENSE
readwise_django_rq_scheduler-1.2.1.dist-info/METADATA
readwise_django_rq_scheduler-1.2.1.dist-info/WHEEL
readwise_django_rq_scheduler-1.2.1.dist-info/top_level.txt
readwise_django_rq_scheduler-1.2.1.dist-info/zip-safe
readwise_django_rq_scheduler-1.2.1.dist-info/RECORD
