Metadata-Version: 2.1
Name: readwise-django-rq-scheduler
Version: 1.2.1
Summary: A database backed job scheduler for Django RQ
Home-page: https://github.com/isl-x/django-rq-scheduler
Author: Chad Shryock
Author-email: chad@keystone.works
License: UNKNOWN
Platform: UNKNOWN
Classifier: Development Status :: 4 - Beta
Classifier: Environment :: Web Environment
Classifier: Intended Audience :: Developers
Classifier: License :: OSI Approved :: MIT License
Classifier: Operating System :: OS Independent
Classifier: Programming Language :: Python
Classifier: Programming Language :: Python :: 3.6
Classifier: Programming Language :: Python :: 3.7
Classifier: Programming Language :: Python :: 3.8
Classifier: Framework :: Django
Classifier: Framework :: Django :: 2.0
Classifier: Framework :: Django :: 3.0
Requires-Dist: django (>=2.0)
Requires-Dist: django-model-utils (>=2.4.0)
Requires-Dist: django-rq (>=0.9.3)
Requires-Dist: rq-scheduler (>=0.6.0)
Requires-Dist: pytz (>=2015.7)
Requires-Dist: croniter (>=0.3.24)
Provides-Extra: test
Requires-Dist: factory-boy (>=2.11.1) ; extra == 'test'
